otio_cdl_adapter/__init__.py
otio_cdl_adapter/cdl_adapter.py
otio_cdl_adapter/plugin_manifest.json
otio_cdl_adapter/utils.py
otio_cdl_adapter-0.8.dist-info/LICENSE-MIT
otio_cdl_adapter-0.8.dist-info/METADATA
otio_cdl_adapter-0.8.dist-info/WHEEL
otio_cdl_adapter-0.8.dist-info/entry_points.txt
otio_cdl_adapter-0.8.dist-info/top_level.txt
otio_cdl_adapter-0.8.dist-info/RECORD
